inhum/__init__.py
inhum/_modidx.py
inhum/core.py
inhum-0.0.8.dist-info/LICENSE
inhum-0.0.8.dist-info/METADATA
inhum-0.0.8.dist-info/WHEEL
inhum-0.0.8.dist-info/entry_points.txt
inhum-0.0.8.dist-info/top_level.txt
inhum-0.0.8.dist-info/RECORD
